nitaq
