Metadata-Version: 2.1
Name: nitaq
Version: 1.4.0
Summary: Nitaq
Home-page: UNKNOWN
Author: Mustafa
Author-email: mustafa.alhamad.sa@gmail.com
License: UNKNOWN
Platform: UNKNOWN
